example-spi/spi_slave_tang/src/spi_slave.v
module spi_slave
(
	input [7:0] data_out,
	output reg [7:0] data_in,

	input SCLK,
	input MOSI,
	output MISO,
	input SS
);

reg state;
reg [2:0] data_counter;

initial
begin
	data_in <= 0;
	state <= 0;
	data_counter <= 0;
end

always @(posedge SCLK)
begin
	if (!SS)
	begin
		if (!state)
		begin
			state = 1;
			data_counter = 7;
		end

		data_in = { data_in[6:0], MOSI };
		if (data_counter == 0) state = 0;
		data_counter = data_counter - 1;
	end
end

assign MISO = state;

endmodule

example-spi/spi_tang/src/spi.v
module spi_master
(
	input clk,
	input start,
	input [7:0] data_out,
	output reg [7:0] data_in,

	output reg SCLK,
	output reg MOSI,
	input MISO,
	output reg SS
);

reg [1:0] state;
reg [2:0] data_counter;

initial
begin
	data_in <= 0;
	state <= 0;
	SS <= 1;
	MOSI <= 0;
	SCLK <= 0;
	data_counter <= 0;
end

always @(posedge clk)
begin
	case (state)
		0:
		begin
			if (start) // If not transmitting but commanded to start
			begin
				state <= 1;

				SS <= 0;
				SCLK <= 0;
				data_counter <= 7;
				MOSI <= data_out[7];
			end
		end
		1: // If transmitting
		begin
			if (!SCLK) // If making a posedge
			begin		
				data_in[data_counter] <= MISO;

				if (!data_counter)
					state <= 2;
				else
					data_counter <= data_counter - 1'b1;
			end
			else
			begin
				MOSI <= data_out[data_counter];
			end

			SCLK <= ~SCLK;
		end
		2: // If packets sent
		begin
			SCLK <= 0;
			state <= 3;
			MOSI <= 0;
		end
		3: // If ending transmission
		begin
			SS <= 1;
			state <= 0;
		end
	endcase
end

endmodule

example-spi/spi_tang/src/spi_tb.v
`timescale 1ns / 1ns

module spi_tb();

reg clk;
reg start;

reg [7:0] data_out_m;
wire [7:0] data_in_m;

reg [7:0] data_out_s;
wire [7:0] data_in_s;

wire SCLK;
wire MOSI;
wire MISO;
wire SS;

spi_master m (clk, start, data_out_m, data_in_m, SCLK, MOSI, MISO, SS);
spi_slave s (data_out_s, data_in_s, SCLK, MOSI, MISO, SS);

initial
begin
	clk = 0;
	start = 0;
	data_out_m = 134;
	data_out_s = 79;
	
	#10 start = 1;
	#20 start = 0;
end

initial forever #5 clk = !clk;

initial #1000 $finish;

initial
begin
	$dumpfile("spi.vcd");
	$dumpvars(0, spi_tb);
end

endmodule

example-spi/spi_tang/src/spi.vcd
$date
	Sun Sep 22 18:41:58 2024
$end
$version
	Icarus Verilog
$end
$timescale
	1ns
$end
$scope module spi_tb $end
$var wire 8 ! data_in_s [7:0] $end
$var wire 8 " data_in_m [7:0] $end
$var wire 1 # SS $end
$var wire 1 $ SCLK $end
$var wire 1 % MOSI $end
$var wire 1 & MISO $end
$var reg 1 ' clk $end
$var reg 8 ( data_out_m [7:0] $end
$var reg 8 ) data_out_s [7:0] $end
$var reg 1 * start $end
$scope module m $end
$var wire 1 ' clk $end
$var wire 8 + data_out [7:0] $end
$var wire 1 * start $end
$var wire 1 & MISO $end
$var reg 1 % MOSI $end
$var reg 1 $ SCLK $end
$var reg 1 # SS $end
$var reg 3 , data_counter [2:0] $end
$var reg 8 - data_in [7:0] $end
$var reg 2 . state [1:0] $end
$upscope $end
$scope module s $end
$var wire 1 & MISO $end
$var wire 1 % MOSI $end
$var wire 1 $ SCLK $end
$var wire 1 # SS $end
$var wire 8 / data_out [7:0] $end
$var reg 3 0 data_counter [2:0] $end
$var reg 8 1 data_in [7:0] $end
$var reg 1 2 state $end
$upscope $end
$upscope $end
$enddefinitions $end
$comment Show the parameter values. $end
$dumpall
$end
#0
$dumpvars
02
b0 1
b0 0
b1001111 /
b0 .
b0 -
b0 ,
b10000110 +
0*
b1001111 )
b10000110 (
0'
0&
0%
0$
1#
b0 "
b0 !
$end
#5
1'
#10
0'
1*
#15
1%
b111 ,
0#
b1 .
1'
#20
0'
#25
b1 !
b1 1
b110 0
1&
12
1$
b110 ,
1'
#30
0'
0*
#35
0$
0%
1'
#40
0'
#45
b101 0
b10 !
b10 1
1$
b101 ,
b1000000 "
b1000000 -
1'
#50
0'
#55
0$
1'
#60
0'
#65
b100 0
b100 !
b100 1
1$
b100 ,
b1100000 "
b1100000 -
1'
#70
0'
#75
0$
1'
#80
0'
#85
b11 0
b1000 !
b1000 1
1$
b11 ,
b1110000 "
b1110000 -
1'
#90
0'
#95
0$
1'
#100
0'
#105
b10 0
b10000 !
b10000 1
1$
b10 ,
b1111000 "
b1111000 -
1'
#110
0'
#115
0$
1%
1'
#120
0'
#125
b1 0
b100001 !
b100001 1
1$
b1 ,
b1111100 "
b1111100 -
1'
#130
0'
#135
0$
1'
#140
0'
#145
b0 0
b1000011 !
b1000011 1
1$
b0 ,
b1111110 "
b1111110 -
1'
#150
0'
#155
0$
0%
1'
#160
0'
#165
b111 0
0&
02
b10000110 !
b10000110 1
1$
b10 .
b1111111 "
b1111111 -
1'
#170
0'
#175
b11 .
0$
1'
#180
0'
#185
b0 .
1#
1'
